setup.cfg
setup.py
fabric_gce_tools/__init__.py
fabric_gce_tools.egg-info/PKG-INFO
fabric_gce_tools.egg-info/SOURCES.txt
fabric_gce_tools.egg-info/dependency_links.txt
fabric_gce_tools.egg-info/requires.txt
fabric_gce_tools.egg-info/top_level.txt