Metadata-Version: 1.1
Name: fabric-gce-tools
Version: 0.6
Summary: Fabric integration with Google Compute Engine (GCE)
Home-page: http://github.com/erans/fabric-gce-tools
Author: Eran Sandler
Author-email: eran@sandler.co.il
License: UNKNOWN
Platform: UNKNOWN
Classifier: Development Status :: 5 - Production/Stable
Classifier: Environment :: Console
Classifier: Intended Audience :: Developers
Classifier: Intended Audience :: System Administrators
Classifier: Operating System :: OS Independent
Classifier: Programming Language :: Python :: 2.7
Classifier: Topic :: System :: Clustering
Classifier: Topic :: System :: Systems Administration
Classifier: Topic :: Utilities
